jaxid/__init__.py
jaxid/common.py
jaxid/datasets.py
jaxid/dynonet.py
jaxid/lru.py
jaxid/metrics.py
jaxid/statespace.py
jaxid-0.2.dist-info/LICENSE
jaxid-0.2.dist-info/METADATA
jaxid-0.2.dist-info/WHEEL
jaxid-0.2.dist-info/top_level.txt
jaxid-0.2.dist-info/RECORD
