Metadata-Version: 2.1
Name: jaxid
Version: 0.2
Summary: A code base for system identification with Jax.
Home-page: https://github.com/forgi86/jax-ident
Author: Marco Forgione
Author-email: marco.forgione1986@gmail.com
License-File: LICENSE
Requires-Dist: jax
Requires-Dist: tqdm
Requires-Dist: torch
Requires-Dist: optax
Requires-Dist: scikit-learn
Requires-Dist: scipy
Requires-Dist: nonlinear-benchmarks
Provides-Extra: download_datasets
Requires-Dist: requests ; extra == 'download_datasets'
Requires-Dist: googledrivedownloader ; extra == 'download_datasets'
Provides-Extra: generate_documentation
Requires-Dist: sphinx ; extra == 'generate_documentation'
Provides-Extra: generate_plots
Requires-Dist: matplotlib ; extra == 'generate_plots'
Provides-Extra: open_datasets
Requires-Dist: pandas ; extra == 'open_datasets'
